clashgap/__init__.py
clashgap/_clash.py
clashgap/_fill.py
clashgap/_gap.py
clashgap-1.0.0.dist-info/LICENSE
clashgap-1.0.0.dist-info/WHEEL
clashgap-1.0.0.dist-info/METADATA
clashgap-1.0.0.dist-info/RECORD
