Metadata-Version: 2.1
Name: clashgap
Version: 1.0.0
Summary: A per-character diff/compression algorithm in python
Home-page: https://pypi.org/project/clashgap/
License: MIT
Keywords: diff,compression
Author: NioGreek
Author-email: GreekNio@gmail.com
Requires-Python: >=3.5
Classifier: License :: OSI Approved :: MIT License
Classifier: Programming Language :: Python :: 3
Classifier: Programming Language :: Python :: 3.5
Classifier: Programming Language :: Python :: 3.6
Classifier: Programming Language :: Python :: 3.7
Classifier: Programming Language :: Python :: 3.8
Classifier: Programming Language :: Python :: 3.9
Project-URL: Bug Tracker, https://github.com/NioGreek/Clashgap/issues
Project-URL: Changelog, https://clashgap.readthedocs.io/en/latest/changelog.html
Project-URL: Documentation, https://clashgap.readthedocs.io/en/latest/
Project-URL: Repository, https://github.com/NioGreek/Clashgap
